geometry/__init__.py
geometry/examples.py
geometry/geometry.py
mileva/__init__.py
mileva-0.0.3.dist-info/LICENSE
mileva-0.0.3.dist-info/METADATA
mileva-0.0.3.dist-info/WHEEL
mileva-0.0.3.dist-info/top_level.txt
mileva-0.0.3.dist-info/RECORD
