Metadata-Version: 2.2
Name: mileva
Version: 0.0.3
Summary: Python toolkit for symbolic calculations in general relativity.
Author-email: Frederik De Ceuster <frederik.deceuster@gmail.com>
License:                     GNU GENERAL PUBLIC LICENSE
Project-URL: Homepage, https://github.com/Poincare-code/albert
Keywords: General Relativity,Astrophysics,Astronomy
Classifier: License :: OSI Approved :: GNU General Public License v3 (GPLv3)
Classifier: Programming Language :: Python
Classifier: Programming Language :: Python :: 3
Classifier: Topic :: Scientific/Engineering :: Physics
Classifier: Topic :: Scientific/Engineering :: Astronomy
Requires-Python: >=3.7
License-File: LICENSE
Requires-Dist: numpy
Requires-Dist: scipy
Requires-Dist: numba
Requires-Dist: sympy
Requires-Dist: matplotlib
Requires-Dist: ipywidgets
Requires-Dist: astropy
Requires-Dist: tqdm
Requires-Dist: h5py
Provides-Extra: dev
Requires-Dist: black; extra == "dev"
Requires-Dist: bumpver; extra == "dev"
Requires-Dist: pip-tools; extra == "dev"
Requires-Dist: pytest; extra == "dev"
